unbuffered_input/__init__.py
unbuffered_input/examples.py
unbuffered_input/runloop.py
unbuffered_input-0.0.1.dist-info/METADATA
unbuffered_input-0.0.1.dist-info/RECORD
unbuffered_input-0.0.1.dist-info/WHEEL
unbuffered_input-0.0.1.dist-info/top_level.txt
