Metadata-Version: 2.1
Name: unbuffered-input
Version: 0.0.1
Summary: Unbuffered input from terminal with callbacks
Home-page: https://github.com/masterginger/py-unbuffered-input
Author: Bian Jiang
Author-email: incomingemail2016@gmail.com
License: UNKNOWN
Platform: UNKNOWN
Classifier: Development Status :: 4 - Beta
Classifier: Environment :: Console
Classifier: License :: OSI Approved :: MIT License
Classifier: Operating System :: MacOS :: MacOS X
Classifier: Programming Language :: Python :: 2.7
Classifier: Topic :: Desktop Environment
